{
	"animations": [
		{
			"offsets": [
				-5,
				0
			],
			"loop": false,
			"fps": 24,
			"anim": "idle",
			"indices": [],
			"name": "BF idle dance"
		},
		{
			"offsets": [
				-10,
				-50
			],
			"loop": false,
			"fps": 24,
			"anim": "singDOWN",
			"indices": [],
			"name": "BF NOTE DOWN0"
		},
		{
			"offsets": [
				-29,
				27
			],
			"loop": false,
			"fps": 24,
			"anim": "singUP",
			"indices": [],
			"name": "BF NOTE UP0"
		},
		{
			"offsets": [
				-48,
				-7
			],
			"loop": false,
			"fps": 24,
			"anim": "singLEFT",
			"indices": [],
			"name": "BF NOTE RIGHT0"
		},
		{
			"offsets": [
				-48,
				43
			],
			"loop": false,
			"fps": 24,
			"anim": "singRIGHT",
			"indices": [],
			"name": "BF NOTE LEFT0"
		}
	],
	"no_antialiasing": false,
	"image": "T1/Jr_Assets",
	"position": [
		0,
		350
	],
	"healthicon": "jr",
	"flip_x": true,
	"healthbar_colors": [
		255,
		255,
		156
	],
	"camera_position": [
		0,
		0
	],
	"sing_duration": 4,
	"scale": 1
}